setup.cfg
setup.py
datagod/__init__.py
datagod/datagod.py
datagod/graphtype.py
datagod.egg-info/.DS_Store
datagod.egg-info/PKG-INFO
datagod.egg-info/SOURCES.txt
datagod.egg-info/dependency_links.txt
datagod.egg-info/requires.txt
datagod.egg-info/top_level.txt
datagod/reporter/__init__.py
datagod/reporter/reporter.py
datagod/typevar/__init__.py
datagod/typevar/logtype.py
datagod/typevar/polynomialtype.py
datagod/typevar/typebase.py