Metadata-Version: 1.1
Name: datagod
Version: 0.2.1
Summary: A library focused on faking data
Home-page: https://github.com/gaocegege/Data-God
Author: gaocegege
Author-email: gaocegege@hotmail.com
License: MIT
Download-URL: https://github.com/gaocegege/Data-God/tarball/0.2.1
Keywords: graph,data
Platform: UNKNOWN
